{"pages_cli_build-tools_index.md":"b565b275","pages_cli_index.md":"7a729a40","pages_cli_build-tools_lint.md":"a6946b7a","pages_cli_vite_base.md":"1ee15a2b","index.md":"c3821faf","pages_cli_build-tools_env.md":"768e5746","pages_css_base_css-add.md":"838f023f","pages_cli_webpack_vue.md":"fdcc3ab9","pages_cli_webpack_react.md":"b38ea213","pages_cli_vite_index.md":"ab0d3d3b","pages_cli_vite_vue.md":"53870ea4","pages_cli_webpack_index.md":"93d2be2c","pages_css_base_css.md":"e34c2e77","pages_cli_webpack_base.md":"836afe54","pages_css_other_index.md":"390da399","pages_css_base_index.md":"4d1c3cb5","pages_css_other_practice.md":"60b0276c","pages_css_other_postcss.md":"e4c6e81e","pages_css_base_mobile.md":"88934e7f","pages_css_base_css3.md":"226506ac","pages_css_index.md":"a11349ed","pages_custom_config_index.md":"eceeb2bf","pages_devops_cli_index.md":"2a91914c","pages_expand_skill_window.md":"e1e284bc","pages_devops_deploy_example.md":"977d17ff","pages_devops_deploy_index.md":"f6ef2cdb","pages_devops_deploy_nginx.md":"1e40422b","pages_devops_index.md":"346cbf90","pages_devops_other_index.md":"c161322a","pages_devops_version-control_config.md":"50b84bd9","pages_devops_version-control_git.md":"8892ab74","pages_devops_version-control_index.md":"5f4d5129","pages_electron_base_guide.md":"9e768769","pages_electron_base_message.md":"9be57879","pages_electron_index.md":"3012ce0c","pages_error_base_index.md":"0e83f9c5","pages_error_base_other.md":"94a86044","pages_expand_common_index.md":"cf754c1c","pages_expand_common_linux.md":"08876237","pages_expand_common_markdown.md":"0c5aeaa8","pages_expand_common_nginx.md":"390f1a29","pages_expand_rule_css-rule.md":"1f61a44e","pages_expand_rule_index.md":"7677499d","pages_expand_skill_chrome.md":"ed6b5423","pages_expand_skill_fiddler.md":"7733e195","pages_expand_skill_index.md":"a74f5793","pages_expand_skill_ios.md":"b49f6072","pages_expand_skill_pronunce.md":"b000f289","pages_devops_version-control_github.md":"2ffc843c","pages_error_base_style.md":"6ffd5a94","pages_error_index.md":"914dae19","pages_expand_index.md":"445bf208","pages_js_es6_12.set-map.md":"70b837d2","pages_electron_base_model.md":"59c9c383","pages_error_base_polyfill-three-party.md":"5c9e2198","pages_custom_config_keyboard.md":"fd0ee67b","pages_js_es6_18.generator-async.md":"1edcf036","pages_error_base_polyfill.md":"f3860f75","pages_tk_utils_base.md":"86a02a83","pages_tk_utils_index.md":"e7734ce6","pages_ts_base_1.intro.md":"cb822dd6","pages_ts_base_10.custom_type.md":"43463808","pages_ts_base_11.interface.md":"7c19ebf7","pages_ts_base_12.generics.md":"4c99fd1b","pages_ts_base_13.index_type.md":"95befd7d","pages_js_es6_16.iterator-forof.md":"78a139a4","pages_js_es6_17.generator.md":"010f11a6","pages_electron_base_index.md":"97865680","pages_js_nodejs_index.md":"17cea38a","pages_js_nodejs_module.md":"fec2ed7f","pages_js_nodejs_system-module.md":"1ee334de","pages_js_js_index.md":"9cc39056","pages_js_nodejs_thrid-party-module.md":"341c8510","pages_js_other_ajax.md":"ad1bc53a","pages_js_practice_base.md":"11fdab2a","pages_js_practice_handwrite.md":"5b518182","pages_js_other_regexp.md":"59e44860","pages_js_other_index.md":"787212fd","pages_nextjs_base_dynamic-routes.md":"eec5f189","pages_nextjs_base_index.md":"02ae7258","pages_js_practice_index.md":"c8f4e642","pages_js_practice_three-party.md":"8278fc90","pages_nextjs_base_base.md":"f74e4f62","pages_nextjs_base_pre-render.md":"70c3bedd","pages_nextjs_base_other-options.md":"955c758e","pages_nextjs_base_routes-api.md":"72a6b058","pages_react_base_index.md":"857bc349","pages_nextjs_index.md":"d0d1440d","pages_react_base_react-core.md":"b6d06fa4","pages_react_base_react-router.md":"e244132b","pages_css_other_scss.md":"b8cf4ae2","pages_react_base_react-advance.md":"7516c629","pages_react_parctice_base.md":"d676029d","pages_custom_config_windows.md":"e7105e93","pages_react_index.md":"5ce9c4f3","pages_react_parctice_index.md":"4d7bad9c","pages_custom_program_chrome.md":"7247ace7","pages_react_parctice_three-party.md":"3eb5df2a","pages_custom_index.md":"d589b6d5","pages_tk_index.md":"bf142113","pages_devlog_index.md":"ad3ff1d8","pages_custom_program_vscode.md":"3fc9f998","pages_devlog_react_index.md":"b58569ca","pages_devops_cli_publish.md":"f16a2ee1","pages_devops_cli_pnpm.md":"cbdfc444","pages_devops_cli_yarn.md":"89efbcc5","pages_js_es6_14.reflect.md":"28c82f38","pages_html_index.md":"c8aefd46","pages_html_practice_index.md":"c4d009f7","pages_index.md":"497c08a1","pages_js_es6_10.operator.md":"4ac5e5a5","pages_js_es6_1.babel.md":"945dae25","pages_devops_cli_npm.md":"f0f5fc4c","pages_devops_deploy_deploy.md":"a52b03e5","pages_html_practice_base.md":"65c4f08b","pages_js_es6_11.symbol.md":"2288265b","pages_css_other_styled-components.md":"0625020f","pages_js_es6_13.proxy.md":"f87e7db1","pages_js_es6_2.let-const.md":"88955ffb","pages_js_es6_28.proposals.md":"f082bffc","pages_js_es6_3.destructuring.md":"cbdc61fc","pages_js_es6_4.string.md":"87b345ad","pages_js_es6_5.regex.md":"8e569deb","pages_js_es6_8.array.md":"75af0234","pages_js_index.md":"b8c3481c","pages_js_es6_index.md":"a689015a","pages_devops_cli_apply.md":"227dda68","pages_js_es6_9.object.md":"fc331dd3","pages_js_js_base.md":"5aaae841","pages_js_es6_7.function.md":"cb1ef43b","pages_ts_base_15.build-in_tools_type.md":"8d7ffa87","pages_js_es6_26.arraybuffer.md":"7c3c4e1c","pages_vue2_guide_transition-animation.md":"fdc00f0c","pages_ts_base_5.const.md":"38f26da2","pages_ts_base_6.type_assert.md":"0199a974","pages_ts_base_7.type_inference.md":"990b1bb4","pages_ts_base_8.type_widen.md":"8cfacf31","pages_ts_base_index.md":"696ae618","pages_ts_expand_base.md":"ecde0c3f","pages_ts_expand_other.md":"52e47cc9","pages_ts_expand_react.md":"4b1609dc","pages_ts_expand_essay.md":"a088d63d","pages_ts_base_9.type_narrow.md":"feb51870","pages_ts_expand_index.md":"d4762255","pages_uniapp_base_framework_api.md":"1332cdcb","pages_uniapp_base_index.md":"8aab64e4","pages_uniapp_config_index.md":"5b5ad1d3","pages_uniapp_config_manifest.md":"c2be3fc9","pages_ts_expand_vue3.md":"5ef0c3a2","pages_ts_index.md":"e1e2f4fa","pages_vue3_practice_three-party.md":"931a5c32","pages_uniapp_base_api.md":"937b9dee","pages_uniapp_base_component.md":"0efbc7cf","pages_uniapp_base_config.md":"9dc0123f","pages_vue3_practice_index.md":"a299ad90","pages_uniapp_other_config.md":"b685f544","pages_uniapp_other_index.md":"e89edad7","pages_vue3_vue3_index.md":"66ceedb5","pages_uniapp_config_other.md":"3385383b","pages_uniapp_config_page.md":"682037d9","pages_custom_program_index.md":"82d8bb9f","pages_ts_base_14.map_type.md":"8a978192","pages_js_es6_24.style.md":"638c2a26","pages_devlog_other_index.md":"9b49380e","pages_js_es6_27.decorator.md":"ee005a7d","pages_uniapp_index.md":"e0429952","pages_vue2_guide_reference.md":"3a20b62a","pages_vue2_index.md":"5a96bd2e","pages_vue2_practice_base.md":"8903689c","pages_vue2_practice_index.md":"d2ceb128","pages_uniapp_other_third-party.md":"a13fc851","pages_uniapp_other_wx-compitable.md":"257821a8","pages_ts_base_4.tuple.md":"6d371051","pages_ts_base_2.type.md":"9ad536d8","pages_vue2_data_index.md":"94db5267","pages_ts_base_17.reference.md":"91a32ade","pages_vue2_guide_index.md":"5994554d","pages_ts_base_3.function.md":"41506e8b","pages_js_js_browser.md":"81f370ad","pages_js_es6_19.async.md":"88caa5b2","pages_js_es6_15.promise.md":"42d9102a","pages_js_es6_6.number.md":"5d903169","pages_js_es6_25.async-iterator.md":"6a6c435e","pages_js_es6_21.class-extends.md":"977e9b06","pages_ts_base_16.style_guide.md":"0b936c41","pages_uniapp_other_practice.md":"00bba95a","pages_vue2_guide_reusability-composition.md":"b0fd8dd9","pages_ts_expand_vue2.md":"81f49622","pages_uniapp_base_base.md":"5bdc1ccf","pages_uniapp_other_ios.md":"dfe2571e","pages_vue2_guide_components.md":"aa1f2464","pages_js_es6_20.class-base.md":"7a9ed3ce","pages_vue2_practice_three-party.md":"c6608473","pages_react_base_react-hook.md":"30beb40c","pages_vue2_data_vuex.md":"e4670692","pages_js_es6_23.module-loader.md":"4b623363","pages_vue2_guide_instance.md":"8827baad","pages_js_es6_22.module.md":"76af4578","pages_vue2_router_advance.md":"0ba8ab01","pages_vue2_router_base.md":"8995d763","pages_vue3_guide_index.md":"5d3a16bb","pages_vue3_index.md":"02956e53","pages_vue2_router_index.md":"79033892"}
